README.md
setup.cfg
setup.py
ibm_cloud_security_advisor/__init__.py
ibm_cloud_security_advisor/common.py
ibm_cloud_security_advisor/findings_api_v1.py
ibm_cloud_security_advisor/notifications_api_v1.py
ibm_cloud_security_advisor/version.py
ibm_cloud_security_advisor_test.egg-info/PKG-INFO
ibm_cloud_security_advisor_test.egg-info/SOURCES.txt
ibm_cloud_security_advisor_test.egg-info/dependency_links.txt
ibm_cloud_security_advisor_test.egg-info/requires.txt
ibm_cloud_security_advisor_test.egg-info/top_level.txt