Metadata-Version: 2.1
Name: ibm-cloud-security-advisor-test
Version: 1.1.1
Summary: Test SDK
Home-page: https://github.com/skairali/security-advisor-sdk-python/
Author: IBM Cloud
Author-email: vkalangu@in.ibm.com, skairali@in.ibm.com, ashishth@in.ibm.com
License: Apache 2.0
Keywords: Swagger,Findings API,Notifications API
Platform: UNKNOWN
